{"name":"sign_up_with_email","testCaseName":"Joust.AuthorizationTest","testSteps":[{"number":1,"description":"Is the sign up page","duration":38370,"startTime":1417634582230,"screenshots":[{"screenshot":"33feb6f5d1a985dc211c505de10ab977_NONE.png"}],"result":"SUCCESS","firstScreenshot":{"screenshot":"33feb6f5d1a985dc211c505de10ab977_NONE.png"}},{"number":2,"description":"Enters users credentials: <span class='step-parameter'>email1417634581460@gmail.com, password123</span>","duration":12661,"startTime":1417634620603,"screenshots":[{"screenshot":"d3822f23eeabd44e06be14ae553bdfe9_NONE.png"}],"result":"SUCCESS","firstScreenshot":{"screenshot":"d3822f23eeabd44e06be14ae553bdfe9_NONE.png"}},{"number":3,"description":"Enters first last names: <span class='step-parameter'>test1417634581460, test1417634581460</span>","duration":15560,"startTime":1417634633266,"screenshots":[{"screenshot":"57688b1edca314efaea84304f43a203c_NONE.png"}],"result":"SUCCESS","firstScreenshot":{"screenshot":"57688b1edca314efaea84304f43a203c_NONE.png"}},{"number":4,"description":"Should be logged in: <span class='step-parameter'>test1417634581460</span>","duration":5884,"startTime":1417634648829,"screenshots":[{"screenshot":"65702493b04ca58bcfc9b512b00bafa1_NONE.png"},{"screenshot":"498fe5f870681049924ef44d82205b28_NONE.png"}],"result":"SUCCESS","firstScreenshot":{"screenshot":"65702493b04ca58bcfc9b512b00bafa1_NONE.png"}}],"userStory":{"id":"Joust.requirements.Application.Search.SearchByKeyword","storyName":"Search by keyword","storyClassName":"Joust.requirements.Application$Search$SearchByKeyword","path":"Joust.requirements.Application.Search","feature":{"id":"Joust.requirements.Application.Search","name":"Search"},"type":"story"},"title":"Sign up with email","tags":[{"name":"Search","type":"feature"},{"name":"Search by keyword","type":"story"}],"startTime":1417634582083,"duration":72635,"manual":false,"result":"SUCCESS","feature":{"id":"Joust.requirements.Application.Search","name":"Search"}}